inventree_bulk_plugin/__init__.py
inventree_bulk_plugin/api.py
inventree_bulk_plugin/bulkcreate_objects.py
inventree_bulk_plugin/core.py
inventree_bulk_plugin/models.py
inventree_bulk_plugin/serializers.py
inventree_bulk_plugin/BulkGenerator/BulkGenerator.py
inventree_bulk_plugin/BulkGenerator/__init__.py
inventree_bulk_plugin/BulkGenerator/dimensions.py
inventree_bulk_plugin/BulkGenerator/template.py
inventree_bulk_plugin/BulkGenerator/utils.py
inventree_bulk_plugin/BulkGenerator/validations.py
inventree_bulk_plugin/BulkGenerator/generators/__init__.py
inventree_bulk_plugin/BulkGenerator/generators/gen_alpha.py
inventree_bulk_plugin/BulkGenerator/generators/gen_numeric.py
inventree_bulk_plugin/BulkGenerator/generators/generator.py
inventree_bulk_plugin/migrations/0001_initial.py
inventree_bulk_plugin/migrations/__init__.py
inventree_bulk_plugin/static/bulk-creation-panel.dev.js
inventree_bulk_plugin/static/dist/bulk-creation-panel.js
inventree_bulk_plugin/static/dist/assets/style.css
inventree_bulk_plugin/templates/preact-page.html
inventree_bulk_plugin/tests/__init__.py
inventree_bulk_plugin/tests/integration/__init__.py
inventree_bulk_plugin/tests/integration/test_InvenTreeBulkPlugin.py
inventree_bulk_plugin/tests/integration/test_api.py
inventree_bulk_plugin/tests/integration/test_bulkcreate_objects.py
inventree_bulk_plugin/tests/integration/test_migrations.py
inventree_bulk_plugin/tests/unit/__init__.py
inventree_bulk_plugin/tests/unit/test_BulkGenerator.py
inventree_bulk_plugin/tests/unit/test_dimensions.py
inventree_bulk_plugin/tests/unit/test_generators.py
inventree_bulk_plugin/tests/unit/test_template.py
inventree_bulk_plugin/tests/unit/test_utils.py
inventree_bulk_plugin-1.4.3.dist-info/licenses/LICENSE
inventree_bulk_plugin-1.4.3.dist-info/METADATA
inventree_bulk_plugin-1.4.3.dist-info/WHEEL
inventree_bulk_plugin-1.4.3.dist-info/entry_points.txt
inventree_bulk_plugin-1.4.3.dist-info/top_level.txt
inventree_bulk_plugin-1.4.3.dist-info/RECORD
