Metadata-Version: 2.4
Name: inventree-bulk-plugin
Version: 1.4.3
Summary: Bulk creation plugin for InvenTree
Author-email: wolflu05 <76838159+wolflu05@users.noreply.github.com>
License-Expression: MIT
Project-URL: Homepage, https://github.com/wolflu05/inventree-bulk-plugin
Keywords: inventree,plugin
Classifier: Programming Language :: Python :: 3
Classifier: Operating System :: OS Independent
Classifier: Framework :: InvenTree
Requires-Python: >=3.9
License-File: LICENSE
Requires-Dist: pydantic==2.*
Requires-Dist: Jinja2==3.*
Dynamic: license-file
